{"stem":"A professional soccer player came with a history of trauma on the lateral aspect of the left knee. On examination, there is a reduced range of movements and there is a swelling on the medial aspect of the left knee.\r\n\r\nThe most likely diagnosis is","opt1":"Medial collateral ligament injury","opt2":"Lateral collateral ligament injury","opt3":"Medial meniscus tear","opt4":"Lateral meniscus tear","disc":"Medial Collateral Ligament (MCL) injury is the most common athletic knee injury. It usually results in a lateral blow to the knee. It may occur in isolation or together with a meniscal or anterior cruciate ligament injury.\r\n\r\nGrade I - minor and stable\r\nGrade II - partial tear with some degree of instability\r\nGrade III - complete tear with gross instability\r\n\r\nOn examination, there may be swelling, bruising, or deformity. Special tests include anterior and posterior drawer, Lachman, and valgus\/varus stress.\r\n\r\nDiagnosis can be confirmed with MRI.\r\n\r\nFor isolated MCL injury, the management is often conservative. Gross instability and failure of conservative measures warrant reconstructive surgery.","ref":"UpToDate and MTB Step 2 CK","tags":"Orthopedics, Sports","_id":205}