{"id":54,"stem":"A 23-year-old female consulted her doctor because of a breast mass. It is mobile, firm, and approximately 1cm in diameter. It is located in the upper outer quadrant of the right breast. No axillary lymph nodes are felt during the examination. What is the treatment of choice for this condition?","opt1":"Modified radical mastectomy","opt2":"Lumpectomy and core biopsy","opt3":"Radical mastectomy","opt4":"Watchful waiting","disc":"A fibroadenoma is a mobile well-defined mass that is a benign solid tumor. It has glandular and fibrous tissue histologically. After a USS confirmation, a definitive diagnosis can be obtained with a core needle biopsy. \r\n\r\nIn young patients, observation with repeat USS in 3-6 months can be done in the absence of other significant clinical signs. Excision is required if the size increases significantly to exclude a malignancy.","ref":"MTB Step 2 CK","tags":"Surgery, Breast Mass, Fibroadenoma","_id":54}